taylor_pipelines/__init__.py
taylor_pipelines/argument.py
taylor_pipelines/pipeline.py
taylor_pipelines/process.py
taylor_pipelines/source.py
taylor_pipelines-0.0.1.dist-info/METADATA
taylor_pipelines-0.0.1.dist-info/WHEEL
taylor_pipelines-0.0.1.dist-info/top_level.txt
taylor_pipelines-0.0.1.dist-info/RECORD
